MANIFEST.in
README.md
setup.py
phantomjs_bin/__init__.py
phantomjs_bin/bin/linux/phantomjs
phantomjs_bin/bin/macosx/phantomjs
phantomjs_bin/bin/windows/phantomjs.exe
phantomjs_binary.egg-info/PKG-INFO
phantomjs_binary.egg-info/SOURCES.txt
phantomjs_binary.egg-info/dependency_links.txt
phantomjs_binary.egg-info/top_level.txt