Metadata-Version: 1.0
Name: phantomjs-binary
Version: 2.1.3
Summary: A pip package for installing binary files of phantomjs
Home-page: https://github.com/jayjiahua/phantomjs-bin-pip
Author: jayjiahua
Author-email: jayjhwu@gmail.com
License: UNKNOWN
Platform: UNKNOWN
